dfx/__init__.py
dfx/__main__.py
dfx/datasets.py
dfx/grain.py
dfx/ops.py
dfx/ui.py
dfx/ui_curses.py
dfx/ui_lines.py
tests/__init__.py
tests/test_dfview.py
tests/test_environment.py
tests/test_grain.py
tests/test_incremental_comp.py
tests/test_main.py
tests/test_ops.py
tests/unittest_dfx.py
dfx-0.0.4.dist-info/LICENSE
dfx-0.0.4.dist-info/METADATA
dfx-0.0.4.dist-info/WHEEL
dfx-0.0.4.dist-info/entry_points.txt
dfx-0.0.4.dist-info/top_level.txt
dfx-0.0.4.dist-info/RECORD
