Metadata-Version: 2.1
Name: dfx
Version: 0.0.4
Summary: Navigate small data
Home-page: https://github.com/mclaffey/dfx
Author: Mike Claffey
Author-email: mikeclaffey@yahoo.com
License: UNKNOWN
Platform: UNKNOWN
Classifier: Programming Language :: Python :: 3
Classifier: License :: OSI Approved :: MIT License
Classifier: Operating System :: OS Independent
Requires-Python: >=3.6
